{
  "system": 0,
  "shared": 0,
  "display": "P584307129",
  "help": "P2290135600",
  "shortHelp": "P2290135600",
  "icon": "Claws_Stalker_set.ico",
  "costumeKeys": [],
  "costumeParts": [],
  "accountRequires": "",
  "accountTooltip": "",
  "accountProduct": "",
  "buyRequires": [],
  "buyRequiresFailed": "",
  "showInInventory": 1,
  "showInManage": 1,
  "showInInfo": 1,
  "specializeAt": 0,
  "specializeRequires": [],
  "powers": [
    "V_GenericVillains.Claws_Stalker.Swipe",
    "V_GenericVillains.Claws_Stalker.Strike",
    "V_GenericVillains.Claws_Stalker.Focus",
    "V_GenericVillains.Claws_Stalker.Slash",
    "V_GenericVillains.Claws_Stalker.Focused_Fighting",
    "V_GenericVillains.Claws_Stalker.Assassins_Claw",
    "V_GenericVillains.Claws_Stalker.Shockwave",
    "V_GenericVillains.Claws_Stalker.Inner_Focus",
    "V_GenericVillains.Claws_Stalker.Eviscerate",
    "V_GenericVillains.Claws_Stalker.Quickness",
    "V_GenericVillains.Claws_Stalker.Elude"
  ],
  "available": [
    0,
    0,
    0,
    0,
    0,
    0,
    0,
    0,
    0,
    0,
    0
  ],
  "aimaxLevel": [
    0,
    0,
    0,
    0,
    0,
    0,
    0,
    0,
    0,
    0,
    0
  ],
  "aiminRankCon": [
    4294957297,
    4294957297,
    4294957297,
    4294957297,
    4294957297,
    4294957297,
    4294957297,
    4294957297,
    4294957297,
    4294957297,
    4294957297
  ],
  "aimaxRankCon": [
    9999,
    9999,
    9999,
    9999,
    9999,
    9999,
    9999,
    9999,
    9999,
    9999,
    9999
  ],
  "minDifficulty": [
    2,
    2,
    2,
    2,
    2,
    2,
    2,
    2,
    2,
    2,
    2
  ],
  "maxDifficulty": [
    9999,
    9999,
    9999,
    9999,
    9999,
    9999,
    9999,
    9999,
    9999,
    9999,
    9999
  ],
  "forceLevelBought": 4294967295
}