{
  "system": 0,
  "shared": 0,
  "display": "P2937018680",
  "help": "P32924113",
  "shortHelp": "P2937018680",
  "icon": "Dual_Pistols_set.ico",
  "costumeKeys": [
    "CustomWeapon_DualPistolsRight",
    "CustomWeapon_DualPistolsLeft"
  ],
  "costumeParts": [
    "DualPistolRight_Default",
    "DualPistolLeft_Default"
  ],
  "accountRequires": "",
  "accountTooltip": "",
  "accountProduct": "",
  "buyRequires": [],
  "buyRequiresFailed": "",
  "showInInventory": 1,
  "showInManage": 1,
  "showInInfo": 1,
  "specializeAt": 0,
  "specializeRequires": [],
  "powers": [
    "Sentinel_Ranged.Dual_Pistols.Pistols",
    "Sentinel_Ranged.Dual_Pistols.Dual_Wield",
    "Sentinel_Ranged.Dual_Pistols.Empty_Clips",
    "Sentinel_Ranged.Dual_Pistols.Suppressive_Fire",
    "Sentinel_Ranged.Dual_Pistols.Swap_Ammo",
    "Sentinel_Ranged.Dual_Pistols.Cryo_Ammunition",
    "Sentinel_Ranged.Dual_Pistols.Incendiary_Ammunition",
    "Sentinel_Ranged.Dual_Pistols.Chemical_Ammunition",
    "Sentinel_Ranged.Dual_Pistols.Bullet_Rain",
    "Sentinel_Ranged.Dual_Pistols.Executioners_Shot",
    "Sentinel_Ranged.Dual_Pistols.Piercing_Rounds",
    "Sentinel_Ranged.Dual_Pistols.Hail_of_Bullets"
  ],
  "available": [
    0,
    0,
    1,
    5,
    7,
    4294967295,
    4294967295,
    4294967295,
    11,
    17,
    25,
    31
  ],
  "aimaxLevel": [
    0,
    0,
    0,
    0,
    0,
    0,
    0,
    0,
    0,
    0,
    0,
    0
  ],
  "aiminRankCon": [
    4294957297,
    4294957297,
    4294957297,
    4294957297,
    4294957297,
    4294957297,
    4294957297,
    4294957297,
    4294957297,
    4294957297,
    4294957297,
    4294957297
  ],
  "aimaxRankCon": [
    9999,
    9999,
    9999,
    9999,
    9999,
    9999,
    9999,
    9999,
    9999,
    9999,
    9999,
    9999
  ],
  "minDifficulty": [
    2,
    2,
    2,
    2,
    2,
    2,
    2,
    2,
    2,
    2,
    2,
    2
  ],
  "maxDifficulty": [
    9999,
    9999,
    9999,
    9999,
    9999,
    9999,
    9999,
    9999,
    9999,
    9999,
    9999,
    9999
  ],
  "forceLevelBought": 4294967295
}