{
  "system": 0,
  "shared": 0,
  "display": "P2812804475",
  "help": "P2982330905",
  "shortHelp": "P3943528623",
  "icon": "Crafted_TimeSpace_Manipulation_A_set.ico",
  "costumeKeys": [],
  "costumeParts": [],
  "accountRequires": "",
  "accountTooltip": "",
  "accountProduct": "",
  "buyRequires": [],
  "buyRequiresFailed": "",
  "showInInventory": 1,
  "showInManage": 1,
  "showInInfo": 1,
  "specializeAt": 0,
  "specializeRequires": [],
  "powers": [
    "Boosts.Crafted_TimeSpace_Manipulation_A.Crafted_TimeSpace_Manipulation_A"
  ],
  "available": [
    0
  ],
  "aimaxLevel": [
    0
  ],
  "aiminRankCon": [
    4294957297
  ],
  "aimaxRankCon": [
    9999
  ],
  "minDifficulty": [
    2
  ],
  "maxDifficulty": [
    9999
  ],
  "forceLevelBought": 4294967295
}