{
  "class": "Class_Boss_Grunt",
  "gender": "MALE",
  "description": "These Wolf Spiders have discovered a method to become living ghosts. Though they're not completely used to it, they've already begun to master their new ghostly powers.",
  "groupDescription": "",
  "classDisplay": "",
  "aiConfig": "Default_Ranged",
  "group": 168,
  "powers": [
    {
      "category": "V_Arachnos",
      "powerset": "Ghosts",
      "power": "*",
      "level": 0,
      "remove": false,
      "dontSetStance": false
    },
    {
      "category": "V_Arachnos",
      "powerset": "Ghosts_Boss_Low",
      "power": "*",
      "level": 0,
      "remove": false,
      "dontSetStance": false
    },
    {
      "category": "V_Arachnos",
      "powerset": "Ghosts_Boss",
      "power": "*",
      "level": 0,
      "remove": false,
      "dontSetStance": false
    },
    {
      "category": "V_Arachnos",
      "powerset": "Ghosts_High",
      "power": "*",
      "level": 0,
      "remove": false,
      "dontSetStance": false
    }
  ],
  "levels": [
    {
      "level": 10,
      "display": [
        "Wolf Spider Phantom"
      ],
      "costumes": [
        "Ghost_Wolf_Huntsman_01",
        "Ghost_Wolf_Huntsman_02",
        "Ghost_Wolf_Huntsman_03"
      ],
      "experience": 0
    },
    {
      "level": 11,
      "display": [
        "Wolf Spider Phantom"
      ],
      "costumes": [
        "Ghost_Wolf_Huntsman_01",
        "Ghost_Wolf_Huntsman_02",
        "Ghost_Wolf_Huntsman_03"
      ],
      "experience": 0
    },
    {
      "level": 12,
      "display": [
        "Wolf Spider Phantom"
      ],
      "costumes": [
        "Ghost_Wolf_Huntsman_01",
        "Ghost_Wolf_Huntsman_02",
        "Ghost_Wolf_Huntsman_03"
      ],
      "experience": 0
    },
    {
      "level": 13,
      "display": [
        "Wolf Spider Phantom"
      ],
      "costumes": [
        "Ghost_Wolf_Huntsman_01",
        "Ghost_Wolf_Huntsman_02",
        "Ghost_Wolf_Huntsman_03"
      ],
      "experience": 0
    },
    {
      "level": 14,
      "display": [
        "Wolf Spider Phantom"
      ],
      "costumes": [
        "Ghost_Wolf_Huntsman_01",
        "Ghost_Wolf_Huntsman_02",
        "Ghost_Wolf_Huntsman_03"
      ],
      "experience": 0
    },
    {
      "level": 15,
      "display": [
        "Wolf Spider Phantom"
      ],
      "costumes": [
        "Ghost_Wolf_Huntsman_01",
        "Ghost_Wolf_Huntsman_02",
        "Ghost_Wolf_Huntsman_03"
      ],
      "experience": 0
    },
    {
      "level": 16,
      "display": [
        "Wolf Spider Phantom"
      ],
      "costumes": [
        "Ghost_Wolf_Huntsman_01",
        "Ghost_Wolf_Huntsman_02",
        "Ghost_Wolf_Huntsman_03"
      ],
      "experience": 0
    },
    {
      "level": 17,
      "display": [
        "Wolf Spider Phantom"
      ],
      "costumes": [
        "Ghost_Wolf_Huntsman_01",
        "Ghost_Wolf_Huntsman_02",
        "Ghost_Wolf_Huntsman_03"
      ],
      "experience": 0
    },
    {
      "level": 18,
      "display": [
        "Wolf Spider Phantom"
      ],
      "costumes": [
        "Ghost_Wolf_Huntsman_01",
        "Ghost_Wolf_Huntsman_02",
        "Ghost_Wolf_Huntsman_03"
      ],
      "experience": 0
    }
  ],
  "rank": "BOSS",
  "gang": "Monster",
  "flags": [],
  "spawnLimit": 0,
  "spawnLimitMission": 0,
  "additionalRewards": [],
  "favoriteWeapon": "",
  "skillHpRewards": [],
  "skillStatusRewards": [],
  "rewardScale": 1,
  "powerTags": [
    "HumanSkeleton",
    "Ghost",
    "Undead"
  ],
  "specialPetPower": "",
  "fileName": "DEFS/VILLAINS/ARACHNOS.VILLAIN",
  "fileAge": 1570211065,
  "petCommandStrings": [],
  "petVisibility": 4294967295,
  "petCommandability": 0,
  "customBadgeStat": "",
  "badgeFlags": 0
}