{
  "class": "Class_Lt_Grunt",
  "gender": "MALE",
  "description": "Arachnos no doubt stole the technology for these drones from the Rikti. Or perhaps they bargained for it. Lord Recluse will deal with anyone who gives him what he wants.",
  "groupDescription": "",
  "classDisplay": "",
  "aiConfig": "Default_Ranged",
  "group": 152,
  "powers": [
    {
      "category": "V_Arachnos",
      "powerset": "Guard_Lt",
      "power": "*",
      "level": 0,
      "remove": false,
      "dontSetStance": false
    },
    {
      "category": "V_Arachnos",
      "powerset": "Drone_Flight",
      "power": "*",
      "level": 0,
      "remove": false,
      "dontSetStance": false
    }
  ],
  "levels": [
    {
      "level": 50,
      "display": [
        "Arachnos Drone Coordinator"
      ],
      "costumes": [
        "Arachnos_Police_Drone_LT"
      ],
      "experience": 0
    },
    {
      "level": 51,
      "display": [
        "Arachnos Drone Coordinator"
      ],
      "costumes": [
        "Arachnos_Police_Drone_LT"
      ],
      "experience": 0
    },
    {
      "level": 52,
      "display": [
        "Arachnos Drone Coordinator"
      ],
      "costumes": [
        "Arachnos_Police_Drone_LT"
      ],
      "experience": 0
    },
    {
      "level": 53,
      "display": [
        "Arachnos Drone Coordinator"
      ],
      "costumes": [
        "Arachnos_Police_Drone_LT"
      ],
      "experience": 0
    },
    {
      "level": 54,
      "display": [
        "Arachnos Drone Coordinator"
      ],
      "costumes": [
        "Arachnos_Police_Drone_LT"
      ],
      "experience": 0
    }
  ],
  "rank": "PET",
  "gang": "",
  "flags": [],
  "spawnLimit": 4294967295,
  "spawnLimitMission": 4294967295,
  "additionalRewards": [],
  "favoriteWeapon": "",
  "skillHpRewards": [],
  "skillStatusRewards": [],
  "rewardScale": 1,
  "powerTags": [],
  "specialPetPower": "",
  "fileName": "DEFS/VILLAINS/ARACHNOSENDGAME.VILLAIN",
  "fileAge": 1570211065,
  "petCommandStrings": [],
  "petVisibility": 4294967295,
  "petCommandability": 0,
  "customBadgeStat": "",
  "badgeFlags": 0
}