{
  "class": "Class_Boss_Grunt",
  "gender": "MALE",
  "description": "Dr. Aeon is a brilliant scientist within the ranks of Arachnos, though you wouldn't think it by the way he's treated by bot his superiors and those who 'serve' him.",
  "groupDescription": "Arachnos",
  "classDisplay": "",
  "aiConfig": "Default_Ranged",
  "group": 194,
  "powers": [
    {
      "category": "V_Miscellaneous",
      "powerset": "Professor_Echo_Boss",
      "power": "*",
      "level": 0,
      "remove": false,
      "dontSetStance": false
    },
    {
      "category": "V_Miscellaneous",
      "powerset": "Professor_Echo",
      "power": "*",
      "level": 0,
      "remove": false,
      "dontSetStance": false
    }
  ],
  "levels": [
    {
      "level": 15,
      "display": [
        "Dr. Aeon"
      ],
      "costumes": [
        "Doctor_Echo_Young"
      ],
      "experience": 0
    },
    {
      "level": 16,
      "display": [
        "Dr. Aeon"
      ],
      "costumes": [
        "Doctor_Echo_Young"
      ],
      "experience": 0
    },
    {
      "level": 17,
      "display": [
        "Dr. Aeon"
      ],
      "costumes": [
        "Doctor_Echo_Young"
      ],
      "experience": 0
    },
    {
      "level": 18,
      "display": [
        "Dr. Aeon"
      ],
      "costumes": [
        "Doctor_Echo_Young"
      ],
      "experience": 0
    },
    {
      "level": 19,
      "display": [
        "Dr. Aeon"
      ],
      "costumes": [
        "Doctor_Echo_Young"
      ],
      "experience": 0
    },
    {
      "level": 20,
      "display": [
        "Dr. Aeon"
      ],
      "costumes": [
        "Doctor_Echo_Young"
      ],
      "experience": 0
    },
    {
      "level": 21,
      "display": [
        "Dr. Aeon"
      ],
      "costumes": [
        "Doctor_Echo_Young"
      ],
      "experience": 0
    }
  ],
  "rank": "BOSS",
  "gang": "Monster",
  "flags": [],
  "spawnLimit": 0,
  "spawnLimitMission": 0,
  "additionalRewards": [],
  "favoriteWeapon": "",
  "skillHpRewards": [],
  "skillStatusRewards": [],
  "rewardScale": 1,
  "powerTags": [
    "HumanSkeleton",
    "Human"
  ],
  "specialPetPower": "",
  "fileName": "DEFS/VILLAINS/MISCELLANEOUS.VILLAIN",
  "fileAge": 1570211065,
  "petCommandStrings": [],
  "petVisibility": 4294967295,
  "petCommandability": 0,
  "customBadgeStat": "",
  "badgeFlags": 0
}