{
  "class": "Class_Boss_Grunt",
  "gender": "MALE",
  "description": "He's the top of the heap, the big cheese, the man himself: Johnny Sonata. Everyone knows who Johnny Sonata is. He sung his way up in the world with his golden voice and charming smile. While he still releases platinum-selling albums every year, he spends much of his time running his casino, the Golden Giza. Johnny is an extremely powerful man, and there are many rumors that say he's tied both to the Family and to Arachnos.",
  "groupDescription": "Famous Singer",
  "classDisplay": "",
  "aiConfig": "Default_Ranged",
  "group": 194,
  "powers": [
    {
      "category": "Mission_Maker_Secondary",
      "powerset": "Poison",
      "power": "Envenom",
      "level": 0,
      "remove": false,
      "dontSetStance": false
    },
    {
      "category": "Mission_Maker_Secondary",
      "powerset": "Poison",
      "power": "Weaken",
      "level": 0,
      "remove": false,
      "dontSetStance": false
    },
    {
      "category": "Mission_Maker_Attacks",
      "powerset": "Demon_Summoning",
      "power": "Lash",
      "level": 0,
      "remove": false,
      "dontSetStance": false
    },
    {
      "category": "Mission_Maker_Attacks",
      "powerset": "Demon_Summoning",
      "power": "Corruption",
      "level": 0,
      "remove": false,
      "dontSetStance": false
    },
    {
      "category": "Mission_Maker_Attacks",
      "powerset": "Demon_Summoning",
      "power": "Crack_Whip",
      "level": 0,
      "remove": false,
      "dontSetStance": false
    }
  ],
  "levels": [
    {
      "level": 29,
      "display": [
        "Johnny Sonata"
      ],
      "costumes": [
        "Model_Johnny_Sonata_Entity"
      ],
      "experience": 0
    },
    {
      "level": 30,
      "display": [
        "Johnny Sonata"
      ],
      "costumes": [
        "Model_Johnny_Sonata_Entity"
      ],
      "experience": 0
    },
    {
      "level": 31,
      "display": [
        "Johnny Sonata"
      ],
      "costumes": [
        "Model_Johnny_Sonata_Entity"
      ],
      "experience": 0
    },
    {
      "level": 32,
      "display": [
        "Johnny Sonata"
      ],
      "costumes": [
        "Model_Johnny_Sonata_Entity"
      ],
      "experience": 0
    },
    {
      "level": 33,
      "display": [
        "Johnny Sonata"
      ],
      "costumes": [
        "Model_Johnny_Sonata_Entity"
      ],
      "experience": 0
    },
    {
      "level": 34,
      "display": [
        "Johnny Sonata"
      ],
      "costumes": [
        "Model_Johnny_Sonata_Entity"
      ],
      "experience": 0
    },
    {
      "level": 35,
      "display": [
        "Johnny Sonata"
      ],
      "costumes": [
        "Model_Johnny_Sonata_Entity"
      ],
      "experience": 0
    },
    {
      "level": 36,
      "display": [
        "Johnny Sonata"
      ],
      "costumes": [
        "Model_Johnny_Sonata_Entity"
      ],
      "experience": 0
    },
    {
      "level": 37,
      "display": [
        "Johnny Sonata"
      ],
      "costumes": [
        "Model_Johnny_Sonata_Entity"
      ],
      "experience": 0
    },
    {
      "level": 38,
      "display": [
        "Johnny Sonata"
      ],
      "costumes": [
        "Model_Johnny_Sonata_Entity"
      ],
      "experience": 0
    },
    {
      "level": 39,
      "display": [
        "Johnny Sonata"
      ],
      "costumes": [
        "Model_Johnny_Sonata_Entity"
      ],
      "experience": 0
    },
    {
      "level": 40,
      "display": [
        "Johnny Sonata"
      ],
      "costumes": [
        "Model_Johnny_Sonata_Entity"
      ],
      "experience": 0
    },
    {
      "level": 41,
      "display": [
        "Johnny Sonata"
      ],
      "costumes": [
        "Model_Johnny_Sonata_Entity"
      ],
      "experience": 0
    },
    {
      "level": 42,
      "display": [
        "Johnny Sonata"
      ],
      "costumes": [
        "Model_Johnny_Sonata_Entity"
      ],
      "experience": 0
    },
    {
      "level": 43,
      "display": [
        "Johnny Sonata"
      ],
      "costumes": [
        "Model_Johnny_Sonata_Entity"
      ],
      "experience": 0
    },
    {
      "level": 44,
      "display": [
        "Johnny Sonata"
      ],
      "costumes": [
        "Model_Johnny_Sonata_Entity"
      ],
      "experience": 0
    }
  ],
  "rank": "BOSS",
  "gang": "",
  "flags": [],
  "spawnLimit": 0,
  "spawnLimitMission": 0,
  "additionalRewards": [],
  "favoriteWeapon": "",
  "skillHpRewards": [],
  "skillStatusRewards": [],
  "rewardScale": 1,
  "powerTags": [
    "HumanSkeleton"
  ],
  "specialPetPower": "",
  "fileName": "DEFS/VILLAINS/MISCELLANEOUS.VILLAIN",
  "fileAge": 1570211065,
  "petCommandStrings": [],
  "petVisibility": 4294967295,
  "petCommandability": 0,
  "customBadgeStat": "",
  "badgeFlags": 0
}