{
  "class": "Class_Boss_Elite",
  "gender": "MALE",
  "description": "These unearthly crystals grow form a Shadow Seed, a hardened physical form created when several Nictus fuse together and solidify themselves. Shadow Cysts project a field that allows Nictus to survive for extended periods without a host even on a planet's surface. The Cysts also act like wormholes, allowing Nictus to travel instantly from one cyst to another, even across interstellar distances. If allowed to grow in the right conditions, a Shadow Cyst can flood a world with Nictus.",
  "groupDescription": "",
  "classDisplay": "Object",
  "aiConfig": "Objects_Stationary_Base",
  "group": 67,
  "powers": [
    {
      "category": "Nictus",
      "powerset": "Shadow_Crystal",
      "power": "*",
      "level": 0,
      "remove": false,
      "dontSetStance": false
    }
  ],
  "levels": [
    {
      "level": 1,
      "display": [
        "Shadow Cyst Crystal"
      ],
      "costumes": [
        "Shadow_Crystal"
      ],
      "experience": 0
    },
    {
      "level": 2,
      "display": [
        "Shadow Cyst Crystal"
      ],
      "costumes": [
        "Shadow_Crystal"
      ],
      "experience": 0
    },
    {
      "level": 3,
      "display": [
        "Shadow Cyst Crystal"
      ],
      "costumes": [
        "Shadow_Crystal"
      ],
      "experience": 0
    },
    {
      "level": 4,
      "display": [
        "Shadow Cyst Crystal"
      ],
      "costumes": [
        "Shadow_Crystal"
      ],
      "experience": 0
    },
    {
      "level": 5,
      "display": [
        "Shadow Cyst Crystal"
      ],
      "costumes": [
        "Shadow_Crystal"
      ],
      "experience": 0
    },
    {
      "level": 6,
      "display": [
        "Shadow Cyst Crystal"
      ],
      "costumes": [
        "Shadow_Crystal"
      ],
      "experience": 0
    },
    {
      "level": 7,
      "display": [
        "Shadow Cyst Crystal"
      ],
      "costumes": [
        "Shadow_Crystal"
      ],
      "experience": 0
    },
    {
      "level": 8,
      "display": [
        "Shadow Cyst Crystal"
      ],
      "costumes": [
        "Shadow_Crystal"
      ],
      "experience": 0
    },
    {
      "level": 9,
      "display": [
        "Shadow Cyst Crystal"
      ],
      "costumes": [
        "Shadow_Crystal"
      ],
      "experience": 0
    },
    {
      "level": 10,
      "display": [
        "Shadow Cyst Crystal"
      ],
      "costumes": [
        "Shadow_Crystal"
      ],
      "experience": 0
    },
    {
      "level": 11,
      "display": [
        "Shadow Cyst Crystal"
      ],
      "costumes": [
        "Shadow_Crystal"
      ],
      "experience": 0
    },
    {
      "level": 12,
      "display": [
        "Shadow Cyst Crystal"
      ],
      "costumes": [
        "Shadow_Crystal"
      ],
      "experience": 0
    },
    {
      "level": 13,
      "display": [
        "Shadow Cyst Crystal"
      ],
      "costumes": [
        "Shadow_Crystal"
      ],
      "experience": 0
    },
    {
      "level": 14,
      "display": [
        "Shadow Cyst Crystal"
      ],
      "costumes": [
        "Shadow_Crystal"
      ],
      "experience": 0
    },
    {
      "level": 15,
      "display": [
        "Shadow Cyst Crystal"
      ],
      "costumes": [
        "Shadow_Crystal"
      ],
      "experience": 0
    },
    {
      "level": 16,
      "display": [
        "Shadow Cyst Crystal"
      ],
      "costumes": [
        "Shadow_Crystal"
      ],
      "experience": 0
    },
    {
      "level": 17,
      "display": [
        "Shadow Cyst Crystal"
      ],
      "costumes": [
        "Shadow_Crystal"
      ],
      "experience": 0
    },
    {
      "level": 18,
      "display": [
        "Shadow Cyst Crystal"
      ],
      "costumes": [
        "Shadow_Crystal"
      ],
      "experience": 0
    },
    {
      "level": 19,
      "display": [
        "Shadow Cyst Crystal"
      ],
      "costumes": [
        "Shadow_Crystal"
      ],
      "experience": 0
    },
    {
      "level": 20,
      "display": [
        "Shadow Cyst Crystal"
      ],
      "costumes": [
        "Shadow_Crystal"
      ],
      "experience": 0
    },
    {
      "level": 21,
      "display": [
        "Shadow Cyst Crystal"
      ],
      "costumes": [
        "Shadow_Crystal"
      ],
      "experience": 0
    },
    {
      "level": 22,
      "display": [
        "Shadow Cyst Crystal"
      ],
      "costumes": [
        "Shadow_Crystal"
      ],
      "experience": 0
    },
    {
      "level": 23,
      "display": [
        "Shadow Cyst Crystal"
      ],
      "costumes": [
        "Shadow_Crystal"
      ],
      "experience": 0
    },
    {
      "level": 24,
      "display": [
        "Shadow Cyst Crystal"
      ],
      "costumes": [
        "Shadow_Crystal"
      ],
      "experience": 0
    },
    {
      "level": 25,
      "display": [
        "Shadow Cyst Crystal"
      ],
      "costumes": [
        "Shadow_Crystal"
      ],
      "experience": 0
    },
    {
      "level": 26,
      "display": [
        "Shadow Cyst Crystal"
      ],
      "costumes": [
        "Shadow_Crystal"
      ],
      "experience": 0
    },
    {
      "level": 27,
      "display": [
        "Shadow Cyst Crystal"
      ],
      "costumes": [
        "Shadow_Crystal"
      ],
      "experience": 0
    },
    {
      "level": 28,
      "display": [
        "Shadow Cyst Crystal"
      ],
      "costumes": [
        "Shadow_Crystal"
      ],
      "experience": 0
    },
    {
      "level": 29,
      "display": [
        "Shadow Cyst Crystal"
      ],
      "costumes": [
        "Shadow_Crystal"
      ],
      "experience": 0
    },
    {
      "level": 30,
      "display": [
        "Shadow Cyst Crystal"
      ],
      "costumes": [
        "Shadow_Crystal"
      ],
      "experience": 0
    },
    {
      "level": 31,
      "display": [
        "Shadow Cyst Crystal"
      ],
      "costumes": [
        "Shadow_Crystal"
      ],
      "experience": 0
    },
    {
      "level": 32,
      "display": [
        "Shadow Cyst Crystal"
      ],
      "costumes": [
        "Shadow_Crystal"
      ],
      "experience": 0
    },
    {
      "level": 33,
      "display": [
        "Shadow Cyst Crystal"
      ],
      "costumes": [
        "Shadow_Crystal"
      ],
      "experience": 0
    },
    {
      "level": 34,
      "display": [
        "Shadow Cyst Crystal"
      ],
      "costumes": [
        "Shadow_Crystal"
      ],
      "experience": 0
    },
    {
      "level": 35,
      "display": [
        "Shadow Cyst Crystal"
      ],
      "costumes": [
        "Shadow_Crystal"
      ],
      "experience": 0
    },
    {
      "level": 36,
      "display": [
        "Shadow Cyst Crystal"
      ],
      "costumes": [
        "Shadow_Crystal"
      ],
      "experience": 0
    },
    {
      "level": 37,
      "display": [
        "Shadow Cyst Crystal"
      ],
      "costumes": [
        "Shadow_Crystal"
      ],
      "experience": 0
    },
    {
      "level": 38,
      "display": [
        "Shadow Cyst Crystal"
      ],
      "costumes": [
        "Shadow_Crystal"
      ],
      "experience": 0
    },
    {
      "level": 39,
      "display": [
        "Shadow Cyst Crystal"
      ],
      "costumes": [
        "Shadow_Crystal"
      ],
      "experience": 0
    },
    {
      "level": 40,
      "display": [
        "Shadow Cyst Crystal"
      ],
      "costumes": [
        "Shadow_Crystal"
      ],
      "experience": 0
    },
    {
      "level": 41,
      "display": [
        "Shadow Cyst Crystal"
      ],
      "costumes": [
        "Shadow_Crystal"
      ],
      "experience": 0
    },
    {
      "level": 42,
      "display": [
        "Shadow Cyst Crystal"
      ],
      "costumes": [
        "Shadow_Crystal"
      ],
      "experience": 0
    },
    {
      "level": 43,
      "display": [
        "Shadow Cyst Crystal"
      ],
      "costumes": [
        "Shadow_Crystal"
      ],
      "experience": 0
    },
    {
      "level": 44,
      "display": [
        "Shadow Cyst Crystal"
      ],
      "costumes": [
        "Shadow_Crystal"
      ],
      "experience": 0
    },
    {
      "level": 45,
      "display": [
        "Shadow Cyst Crystal"
      ],
      "costumes": [
        "Shadow_Crystal"
      ],
      "experience": 0
    },
    {
      "level": 46,
      "display": [
        "Shadow Cyst Crystal"
      ],
      "costumes": [
        "Shadow_Crystal"
      ],
      "experience": 0
    },
    {
      "level": 47,
      "display": [
        "Shadow Cyst Crystal"
      ],
      "costumes": [
        "Shadow_Crystal"
      ],
      "experience": 0
    },
    {
      "level": 48,
      "display": [
        "Shadow Cyst Crystal"
      ],
      "costumes": [
        "Shadow_Crystal"
      ],
      "experience": 0
    },
    {
      "level": 49,
      "display": [
        "Shadow Cyst Crystal"
      ],
      "costumes": [
        "Shadow_Crystal"
      ],
      "experience": 0
    },
    {
      "level": 50,
      "display": [
        "Shadow Cyst Crystal"
      ],
      "costumes": [
        "Shadow_Crystal"
      ],
      "experience": 0
    },
    {
      "level": 51,
      "display": [
        "Shadow Cyst Crystal"
      ],
      "costumes": [
        "Shadow_Crystal"
      ],
      "experience": 0
    },
    {
      "level": 52,
      "display": [
        "Shadow Cyst Crystal"
      ],
      "costumes": [
        "Shadow_Crystal"
      ],
      "experience": 0
    },
    {
      "level": 53,
      "display": [
        "Shadow Cyst Crystal"
      ],
      "costumes": [
        "Shadow_Crystal"
      ],
      "experience": 0
    },
    {
      "level": 54,
      "display": [
        "Shadow Cyst Crystal"
      ],
      "costumes": [
        "Shadow_Crystal"
      ],
      "experience": 0
    }
  ],
  "rank": "ELITE",
  "gang": "",
  "flags": [],
  "spawnLimit": 0,
  "spawnLimitMission": 0,
  "additionalRewards": [],
  "favoriteWeapon": "",
  "skillHpRewards": [],
  "skillStatusRewards": [],
  "rewardScale": 1.5,
  "powerTags": [],
  "specialPetPower": "",
  "fileName": "DEFS/VILLAINS/NICTUS.VILLAIN",
  "fileAge": 1570211065,
  "petCommandStrings": [],
  "petVisibility": 4294967295,
  "petCommandability": 0,
  "customBadgeStat": "",
  "badgeFlags": 0
}