{
  "class": "Class_Minion_Pets",
  "gender": "MALE",
  "description": "",
  "groupDescription": "",
  "classDisplay": "",
  "aiConfig": "Pets_Stationary",
  "group": 1,
  "powers": [
    {
      "category": "Pets",
      "powerset": "ResistAll",
      "power": "*",
      "level": 0,
      "remove": false,
      "dontSetStance": false
    },
    {
      "category": "Pets",
      "powerset": "Warburg_Afterglow",
      "power": "*",
      "level": 0,
      "remove": false,
      "dontSetStance": false
    }
  ],
  "levels": [
    {
      "level": 1,
      "display": [
        "After Effects"
      ],
      "costumes": [
        "Puddle"
      ],
      "experience": 0
    },
    {
      "level": 2,
      "display": [
        "After Effects"
      ],
      "costumes": [
        "Puddle"
      ],
      "experience": 0
    },
    {
      "level": 3,
      "display": [
        "After Effects"
      ],
      "costumes": [
        "Puddle"
      ],
      "experience": 0
    },
    {
      "level": 4,
      "display": [
        "After Effects"
      ],
      "costumes": [
        "Puddle"
      ],
      "experience": 0
    },
    {
      "level": 5,
      "display": [
        "After Effects"
      ],
      "costumes": [
        "Puddle"
      ],
      "experience": 0
    },
    {
      "level": 6,
      "display": [
        "After Effects"
      ],
      "costumes": [
        "Puddle"
      ],
      "experience": 0
    },
    {
      "level": 7,
      "display": [
        "After Effects"
      ],
      "costumes": [
        "Puddle"
      ],
      "experience": 0
    },
    {
      "level": 8,
      "display": [
        "After Effects"
      ],
      "costumes": [
        "Puddle"
      ],
      "experience": 0
    },
    {
      "level": 9,
      "display": [
        "After Effects"
      ],
      "costumes": [
        "Puddle"
      ],
      "experience": 0
    },
    {
      "level": 10,
      "display": [
        "After Effects"
      ],
      "costumes": [
        "Puddle"
      ],
      "experience": 0
    },
    {
      "level": 11,
      "display": [
        "After Effects"
      ],
      "costumes": [
        "Puddle"
      ],
      "experience": 0
    },
    {
      "level": 12,
      "display": [
        "After Effects"
      ],
      "costumes": [
        "Puddle"
      ],
      "experience": 0
    },
    {
      "level": 13,
      "display": [
        "After Effects"
      ],
      "costumes": [
        "Puddle"
      ],
      "experience": 0
    },
    {
      "level": 14,
      "display": [
        "After Effects"
      ],
      "costumes": [
        "Puddle"
      ],
      "experience": 0
    },
    {
      "level": 15,
      "display": [
        "After Effects"
      ],
      "costumes": [
        "Puddle"
      ],
      "experience": 0
    },
    {
      "level": 16,
      "display": [
        "After Effects"
      ],
      "costumes": [
        "Puddle"
      ],
      "experience": 0
    },
    {
      "level": 17,
      "display": [
        "After Effects"
      ],
      "costumes": [
        "Puddle"
      ],
      "experience": 0
    },
    {
      "level": 18,
      "display": [
        "After Effects"
      ],
      "costumes": [
        "Puddle"
      ],
      "experience": 0
    },
    {
      "level": 19,
      "display": [
        "After Effects"
      ],
      "costumes": [
        "Puddle"
      ],
      "experience": 0
    },
    {
      "level": 20,
      "display": [
        "After Effects"
      ],
      "costumes": [
        "Puddle"
      ],
      "experience": 0
    },
    {
      "level": 21,
      "display": [
        "After Effects"
      ],
      "costumes": [
        "Puddle"
      ],
      "experience": 0
    },
    {
      "level": 22,
      "display": [
        "After Effects"
      ],
      "costumes": [
        "Puddle"
      ],
      "experience": 0
    },
    {
      "level": 23,
      "display": [
        "After Effects"
      ],
      "costumes": [
        "Puddle"
      ],
      "experience": 0
    },
    {
      "level": 24,
      "display": [
        "After Effects"
      ],
      "costumes": [
        "Puddle"
      ],
      "experience": 0
    },
    {
      "level": 25,
      "display": [
        "After Effects"
      ],
      "costumes": [
        "Puddle"
      ],
      "experience": 0
    },
    {
      "level": 26,
      "display": [
        "After Effects"
      ],
      "costumes": [
        "Puddle"
      ],
      "experience": 0
    },
    {
      "level": 27,
      "display": [
        "After Effects"
      ],
      "costumes": [
        "Puddle"
      ],
      "experience": 0
    },
    {
      "level": 28,
      "display": [
        "After Effects"
      ],
      "costumes": [
        "Puddle"
      ],
      "experience": 0
    },
    {
      "level": 29,
      "display": [
        "After Effects"
      ],
      "costumes": [
        "Puddle"
      ],
      "experience": 0
    },
    {
      "level": 30,
      "display": [
        "After Effects"
      ],
      "costumes": [
        "Puddle"
      ],
      "experience": 0
    },
    {
      "level": 31,
      "display": [
        "After Effects"
      ],
      "costumes": [
        "Puddle"
      ],
      "experience": 0
    },
    {
      "level": 32,
      "display": [
        "After Effects"
      ],
      "costumes": [
        "Puddle"
      ],
      "experience": 0
    },
    {
      "level": 33,
      "display": [
        "After Effects"
      ],
      "costumes": [
        "Puddle"
      ],
      "experience": 0
    },
    {
      "level": 34,
      "display": [
        "After Effects"
      ],
      "costumes": [
        "Puddle"
      ],
      "experience": 0
    },
    {
      "level": 35,
      "display": [
        "After Effects"
      ],
      "costumes": [
        "Puddle"
      ],
      "experience": 0
    },
    {
      "level": 36,
      "display": [
        "After Effects"
      ],
      "costumes": [
        "Puddle"
      ],
      "experience": 0
    },
    {
      "level": 37,
      "display": [
        "After Effects"
      ],
      "costumes": [
        "Puddle"
      ],
      "experience": 0
    },
    {
      "level": 38,
      "display": [
        "After Effects"
      ],
      "costumes": [
        "Puddle"
      ],
      "experience": 0
    },
    {
      "level": 39,
      "display": [
        "After Effects"
      ],
      "costumes": [
        "Puddle"
      ],
      "experience": 0
    },
    {
      "level": 40,
      "display": [
        "After Effects"
      ],
      "costumes": [
        "Puddle"
      ],
      "experience": 0
    },
    {
      "level": 41,
      "display": [
        "After Effects"
      ],
      "costumes": [
        "Puddle"
      ],
      "experience": 0
    },
    {
      "level": 42,
      "display": [
        "After Effects"
      ],
      "costumes": [
        "Puddle"
      ],
      "experience": 0
    },
    {
      "level": 43,
      "display": [
        "After Effects"
      ],
      "costumes": [
        "Puddle"
      ],
      "experience": 0
    },
    {
      "level": 44,
      "display": [
        "After Effects"
      ],
      "costumes": [
        "Puddle"
      ],
      "experience": 0
    },
    {
      "level": 45,
      "display": [
        "After Effects"
      ],
      "costumes": [
        "Puddle"
      ],
      "experience": 0
    },
    {
      "level": 46,
      "display": [
        "After Effects"
      ],
      "costumes": [
        "Puddle"
      ],
      "experience": 0
    },
    {
      "level": 47,
      "display": [
        "After Effects"
      ],
      "costumes": [
        "Puddle"
      ],
      "experience": 0
    },
    {
      "level": 48,
      "display": [
        "After Effects"
      ],
      "costumes": [
        "Puddle"
      ],
      "experience": 0
    },
    {
      "level": 49,
      "display": [
        "After Effects"
      ],
      "costumes": [
        "Puddle"
      ],
      "experience": 0
    },
    {
      "level": 50,
      "display": [
        "After Effects"
      ],
      "costumes": [
        "Puddle"
      ],
      "experience": 0
    },
    {
      "level": 51,
      "display": [
        "After Effects"
      ],
      "costumes": [
        "Puddle"
      ],
      "experience": 0
    },
    {
      "level": 52,
      "display": [
        "After Effects"
      ],
      "costumes": [
        "Puddle"
      ],
      "experience": 0
    },
    {
      "level": 53,
      "display": [
        "After Effects"
      ],
      "costumes": [
        "Puddle"
      ],
      "experience": 0
    },
    {
      "level": 54,
      "display": [
        "After Effects"
      ],
      "costumes": [
        "Puddle"
      ],
      "experience": 0
    }
  ],
  "rank": "PET",
  "gang": "",
  "flags": [],
  "spawnLimit": 4294967295,
  "spawnLimitMission": 4294967295,
  "additionalRewards": [],
  "favoriteWeapon": "",
  "skillHpRewards": [],
  "skillStatusRewards": [],
  "rewardScale": 1,
  "powerTags": [],
  "specialPetPower": "",
  "fileName": "DEFS/VILLAINS/PETS.VILLAIN",
  "fileAge": 1570211065,
  "petCommandStrings": [],
  "petVisibility": 4294967295,
  "petCommandability": 0,
  "customBadgeStat": "",
  "badgeFlags": 0
}