{
  "class": "Class_Boss_PraetorianGrunt",
  "gender": "MALE",
  "description": "Reese was once one of the 'Top Dogs' within the Powers Division. He went through a falling out with several members of the organization and was thought dead. However, he survived due to the kindness of some strangers within the tunnels of Praetoria. He has been fighting in the wilds of Praetoria ever since, seeking to prove to everyone in Praetoria that he is truly the 'Top Dog', the most powerful super-powered being in Praetoria.",
  "groupDescription": "Powers Division",
  "classDisplay": "Top Dog",
  "aiConfig": "Default_Ranged",
  "group": 108,
  "powers": [
    {
      "category": "PraetorianPolice",
      "powerset": "Reese",
      "power": "*",
      "level": 0,
      "remove": false,
      "dontSetStance": false
    },
    {
      "category": "V_GenericVillains",
      "powerset": "Electrical_Brute_High",
      "power": "Thunderous_Blast",
      "level": 0,
      "remove": false,
      "dontSetStance": false
    },
    {
      "category": "V_GenericVillains",
      "powerset": "Electrical_Brute_Low",
      "power": "Static_Shield",
      "level": 0,
      "remove": false,
      "dontSetStance": false
    },
    {
      "category": "V_GenericVillains",
      "powerset": "Brute_Resistance",
      "power": "Resistance",
      "level": 0,
      "remove": false,
      "dontSetStance": false
    }
  ],
  "levels": [
    {
      "level": 50,
      "display": [
        "Reese"
      ],
      "costumes": [
        "Model_Reese_NoRing"
      ],
      "experience": 0
    },
    {
      "level": 51,
      "display": [
        "Reese"
      ],
      "costumes": [
        "Model_Reese_NoRing"
      ],
      "experience": 0
    },
    {
      "level": 52,
      "display": [
        "Reese"
      ],
      "costumes": [
        "Model_Reese_NoRing"
      ],
      "experience": 0
    },
    {
      "level": 53,
      "display": [
        "Reese"
      ],
      "costumes": [
        "Model_Reese_NoRing"
      ],
      "experience": 0
    },
    {
      "level": 54,
      "display": [
        "Reese"
      ],
      "costumes": [
        "Model_Reese_NoRing"
      ],
      "experience": 0
    }
  ],
  "rank": "BOSS",
  "gang": "",
  "flags": [],
  "spawnLimit": 0,
  "spawnLimitMission": 0,
  "additionalRewards": [],
  "favoriteWeapon": "",
  "skillHpRewards": [],
  "skillStatusRewards": [],
  "rewardScale": 1,
  "powerTags": [
    "HumanSkeleton",
    "Human"
  ],
  "specialPetPower": "",
  "fileName": "DEFS/VILLAINS/PRAETORIANPOLICE.VILLAIN",
  "fileAge": 1570211065,
  "petCommandStrings": [],
  "petVisibility": 4294967295,
  "petCommandability": 0,
  "customBadgeStat": "",
  "badgeFlags": 0
}