{
  "class": "Class_Boss_Grunt",
  "gender": "MALE",
  "description": "With their powerful force fields, heavy weapons, and advanced training, these armor clad Reflections carry enough firepower to stop a tank. They're also almost as hard to hurt, though they are vulnerable to mental assaults.",
  "groupDescription": "Shadow Shard Reflections",
  "classDisplay": "",
  "aiConfig": "Default_Ranged",
  "group": 60,
  "powers": [
    {
      "category": "Rularuu",
      "powerset": "Reflections",
      "power": "*",
      "level": 0,
      "remove": false,
      "dontSetStance": false
    },
    {
      "category": "Crey",
      "powerset": "Crey_Lt_Boss_Armored_Cryo",
      "power": "*",
      "level": 0,
      "remove": false,
      "dontSetStance": false
    },
    {
      "category": "Crey",
      "powerset": "Crey_Lt_Boss_Armored_Melee",
      "power": "*",
      "level": 0,
      "remove": false,
      "dontSetStance": false
    },
    {
      "category": "Crey",
      "powerset": "Crey_Lt_Boss_Armored_Defense",
      "power": "*",
      "level": 0,
      "remove": false,
      "dontSetStance": false
    },
    {
      "category": "Crey",
      "powerset": "Crey_Boss_Armored_Buff",
      "power": "*",
      "level": 0,
      "remove": false,
      "dontSetStance": false
    }
  ],
  "levels": [
    {
      "level": 41,
      "display": [
        "Crey Protector"
      ],
      "costumes": [
        "CRE_04"
      ],
      "experience": 0
    },
    {
      "level": 42,
      "display": [
        "Crey Protector"
      ],
      "costumes": [
        "CRE_04"
      ],
      "experience": 0
    },
    {
      "level": 43,
      "display": [
        "Crey Protector"
      ],
      "costumes": [
        "CRE_04"
      ],
      "experience": 0
    },
    {
      "level": 44,
      "display": [
        "Crey Protector"
      ],
      "costumes": [
        "CRE_04"
      ],
      "experience": 0
    },
    {
      "level": 45,
      "display": [
        "Crey Protector"
      ],
      "costumes": [
        "CRE_04"
      ],
      "experience": 0
    },
    {
      "level": 46,
      "display": [
        "Crey Protector"
      ],
      "costumes": [
        "CRE_04"
      ],
      "experience": 0
    },
    {
      "level": 47,
      "display": [
        "Crey Protector"
      ],
      "costumes": [
        "CRE_04"
      ],
      "experience": 0
    },
    {
      "level": 48,
      "display": [
        "Crey Protector"
      ],
      "costumes": [
        "CRE_04"
      ],
      "experience": 0
    },
    {
      "level": 49,
      "display": [
        "Crey Protector"
      ],
      "costumes": [
        "CRE_04"
      ],
      "experience": 0
    },
    {
      "level": 50,
      "display": [
        "Crey Protector"
      ],
      "costumes": [
        "CRE_04"
      ],
      "experience": 0
    },
    {
      "level": 51,
      "display": [
        "Crey Protector"
      ],
      "costumes": [
        "CRE_04"
      ],
      "experience": 0
    },
    {
      "level": 52,
      "display": [
        "Crey Protector"
      ],
      "costumes": [
        "CRE_04"
      ],
      "experience": 0
    },
    {
      "level": 53,
      "display": [
        "Crey Protector"
      ],
      "costumes": [
        "CRE_04"
      ],
      "experience": 0
    },
    {
      "level": 54,
      "display": [
        "Crey Protector"
      ],
      "costumes": [
        "CRE_04"
      ],
      "experience": 0
    }
  ],
  "rank": "BOSS",
  "gang": "",
  "flags": [],
  "spawnLimit": 4294967295,
  "spawnLimitMission": 4294967295,
  "additionalRewards": [],
  "favoriteWeapon": "",
  "skillHpRewards": [],
  "skillStatusRewards": [],
  "rewardScale": 1,
  "powerTags": [
    "HumanSkeleton"
  ],
  "specialPetPower": "",
  "fileName": "DEFS/VILLAINS/REFLECTIONS.VILLAIN",
  "fileAge": 1570211065,
  "petCommandStrings": [],
  "petVisibility": 4294967295,
  "petCommandability": 0,
  "customBadgeStat": "",
  "badgeFlags": 0
}