{
  "system": 0,
  "shared": 0,
  "display": "Assault Rifle",
  "help": "The Assault Rifle is a state-of-the-art piece of hardware. It is equipped to handle an impressive arsenal of munitions and firing modes. The Assault Rifle is also equipped with the latest in targeting technology, and is a very accurate weapon.",
  "shortHelp": "Assault Rifle",
  "icon": "Assault_Rifle_set.ico",
  "costumeKeys": [
    "CustomWeapon_AssaultRifle"
  ],
  "costumeParts": [
    "AssaultRifle_Default"
  ],
  "accountRequires": "",
  "accountTooltip": "",
  "accountProduct": "",
  "buyRequires": [],
  "buyRequiresFailed": "",
  "showInInventory": 1,
  "showInManage": 1,
  "showInInfo": 1,
  "specializeAt": 0,
  "specializeRequires": [],
  "powers": [
    "Mission_Maker_Secondary.Assault_Rifle.Burst",
    "Mission_Maker_Secondary.Assault_Rifle.Slug",
    "Mission_Maker_Secondary.Assault_Rifle.Buckshot",
    "Mission_Maker_Secondary.Assault_Rifle.M30_Grenade",
    "Mission_Maker_Secondary.Assault_Rifle.Beanbag",
    "Mission_Maker_Secondary.Assault_Rifle.Flamethrower",
    "Mission_Maker_Secondary.Assault_Rifle.Ignite",
    "Mission_Maker_Secondary.Assault_Rifle.Full_Auto"
  ],
  "available": [
    0,
    0,
    1,
    5,
    7,
    17,
    25,
    31
  ],
  "aimaxLevel": [
    0,
    0,
    0,
    0,
    0,
    0,
    0,
    0
  ],
  "aiminRankCon": [
    4294957297,
    4294957297,
    1,
    0,
    0,
    2,
    1,
    0
  ],
  "aimaxRankCon": [
    9999,
    9999,
    9999,
    9999,
    9999,
    9999,
    9999,
    9999
  ],
  "minDifficulty": [
    4294967295,
    4294967295,
    4294967295,
    1,
    1,
    4294967295,
    1,
    2
  ],
  "maxDifficulty": [
    9999,
    9999,
    9999,
    9999,
    9999,
    9999,
    9999,
    9999
  ],
  "forceLevelBought": 4294967295
}