{
  "system": 0,
  "shared": 0,
  "display": "Chi Master",
  "help": "Chi Master",
  "shortHelp": "Chi Master",
  "icon": "Chi_Master_set.ico",
  "costumeKeys": [],
  "costumeParts": [],
  "accountRequires": "",
  "accountTooltip": "",
  "accountProduct": "",
  "buyRequires": [],
  "buyRequiresFailed": "",
  "showInInventory": 1,
  "showInManage": 1,
  "showInInfo": 1,
  "specializeAt": 0,
  "specializeRequires": [],
  "powers": [
    "Tsoo.Chi_Master.Quick_Strike",
    "Tsoo.Chi_Master.Smashing_Blow",
    "Tsoo.Chi_Master.Repulsing_Torrent",
    "Tsoo.Chi_Master.Burst",
    "Tsoo.Chi_Master.Focused_Burst",
    "Tsoo.Chi_Master.High_Pain_Tolerance",
    "Tsoo.Chi_Master.Quick_Recovery",
    "Tsoo.Chi_Master.Heightened_Senses"
  ],
  "available": [
    0,
    29,
    0,
    29,
    0,
    0,
    0,
    29
  ],
  "aimaxLevel": [
    0,
    0,
    0,
    0,
    0,
    0,
    0,
    0
  ],
  "aiminRankCon": [
    4294957297,
    4294957297,
    4294957297,
    4294957297,
    4294957297,
    4294957297,
    4294957297,
    4294957297
  ],
  "aimaxRankCon": [
    9999,
    9999,
    9999,
    9999,
    9999,
    9999,
    9999,
    9999
  ],
  "minDifficulty": [
    2,
    2,
    2,
    2,
    2,
    2,
    2,
    2
  ],
  "maxDifficulty": [
    9999,
    9999,
    9999,
    9999,
    9999,
    9999,
    9999,
    9999
  ],
  "forceLevelBought": 4294967295
}