{
  "system": 0,
  "shared": 0,
  "display": "P2665551719",
  "help": "P1603422892",
  "shortHelp": "P2665551719",
  "icon": "Plant_Control_set.ico",
  "costumeKeys": [],
  "costumeParts": [],
  "accountRequires": "",
  "accountTooltip": "",
  "accountProduct": "",
  "buyRequires": [],
  "buyRequiresFailed": "",
  "showInInventory": 1,
  "showInManage": 1,
  "showInInfo": 1,
  "specializeAt": 0,
  "specializeRequires": [],
  "powers": [
    "Controller_Control.Plant_Control.Entangle",
    "Controller_Control.Plant_Control.Strangler",
    "Controller_Control.Plant_Control.Roots",
    "Controller_Control.Plant_Control.Spore_Burst",
    "Controller_Control.Plant_Control.Seeds_of_Confusion",
    "Controller_Control.Plant_Control.Spirit_Tree",
    "Controller_Control.Plant_Control.Vines",
    "Controller_Control.Plant_Control.Carrion_Creepers",
    "Controller_Control.Plant_Control.Fly_Trap"
  ],
  "available": [
    0,
    0,
    1,
    5,
    7,
    11,
    17,
    25,
    31
  ],
  "aimaxLevel": [
    0,
    0,
    0,
    0,
    0,
    0,
    0,
    0,
    0
  ],
  "aiminRankCon": [
    4294957297,
    4294957297,
    4294957297,
    4294957297,
    4294957297,
    4294957297,
    4294957297,
    4294957297,
    4294957297
  ],
  "aimaxRankCon": [
    9999,
    9999,
    9999,
    9999,
    9999,
    9999,
    9999,
    9999,
    9999
  ],
  "minDifficulty": [
    2,
    2,
    2,
    2,
    2,
    2,
    2,
    2,
    2
  ],
  "maxDifficulty": [
    9999,
    9999,
    9999,
    9999,
    9999,
    9999,
    9999,
    9999,
    9999
  ],
  "forceLevelBought": 4294967295
}