{
  "system": 0,
  "shared": 0,
  "display": "P1849979927",
  "help": "P3190575417",
  "shortHelp": "P1849979927",
  "icon": "Necromancy_set.ico",
  "costumeKeys": [],
  "costumeParts": [],
  "accountRequires": "",
  "accountTooltip": "",
  "accountProduct": "",
  "buyRequires": [],
  "buyRequiresFailed": "",
  "showInInventory": 1,
  "showInManage": 1,
  "showInInfo": 1,
  "specializeAt": 0,
  "specializeRequires": [],
  "powers": [
    "Mastermind_Summon.Necromancy.Dark_Blast",
    "Mastermind_Summon.Necromancy.Zombie_Horde",
    "Mastermind_Summon.Necromancy.Gloom",
    "Mastermind_Summon.Necromancy.Enchant_Undead",
    "Mastermind_Summon.Necromancy.Life_Drain",
    "Mastermind_Summon.Necromancy.Skeletal_Warriors",
    "Mastermind_Summon.Necromancy.Soul_Extraction",
    "Mastermind_Summon.Necromancy.Lich",
    "Mastermind_Summon.Necromancy.Dark_Empowerment"
  ],
  "available": [
    0,
    0,
    1,
    5,
    7,
    11,
    17,
    25,
    31
  ],
  "aimaxLevel": [
    0,
    0,
    0,
    0,
    0,
    0,
    0,
    0,
    0
  ],
  "aiminRankCon": [
    4294957297,
    4294957297,
    4294957297,
    4294957297,
    4294957297,
    4294957297,
    4294957297,
    4294957297,
    4294957297
  ],
  "aimaxRankCon": [
    9999,
    9999,
    9999,
    9999,
    9999,
    9999,
    9999,
    9999,
    9999
  ],
  "minDifficulty": [
    2,
    2,
    2,
    2,
    2,
    2,
    2,
    2,
    2
  ],
  "maxDifficulty": [
    9999,
    9999,
    9999,
    9999,
    9999,
    9999,
    9999,
    9999,
    9999
  ],
  "forceLevelBought": 4294967295
}